bio_tool_version_manager/__init__.py
bio_tool_version_manager/cli.py
bio_tool_version_manager/insert.py
bio_tool_version_manager/io.py
bio_tool_version_manager/models.py
bio_tool_version_manager-1.2.0.dist-info/licenses/LICENSE
bio_tool_version_manager-1.2.0.dist-info/METADATA
bio_tool_version_manager-1.2.0.dist-info/WHEEL
bio_tool_version_manager-1.2.0.dist-info/entry_points.txt
bio_tool_version_manager-1.2.0.dist-info/top_level.txt
bio_tool_version_manager-1.2.0.dist-info/RECORD
