Metadata-Version: 2.4
Name: bio_tool_version_manager
Version: 1.2.0
Summary: Allows management of tool and workflow version in database and json
Home-page: https://github.com/ages-bioinformatics/bio_tool_version_manager
Author: Patrick Hyden
Author-email: patrick.hyden@ages.at
Classifier: Programming Language :: Python :: 3
Classifier: License :: OSI Approved :: MIT License
Classifier: Operating System :: OS Independent
Requires-Python: >=3.6
License-File: LICENSE
Dynamic: author
Dynamic: author-email
Dynamic: classifier
Dynamic: description
Dynamic: description-content-type
Dynamic: home-page
Dynamic: license-file
Dynamic: requires-python
Dynamic: summary
